mplsignal/__init__.py
mplsignal/_api.py
mplsignal/_utils.py
mplsignal/_version.py
mplsignal/freq_plots.py
mplsignal/plane_plots.py
mplsignal/scipyplot.py
mplsignal/ticker.py
mplsignal-0.2.0.dist-info/LICENSE
mplsignal-0.2.0.dist-info/METADATA
mplsignal-0.2.0.dist-info/WHEEL
mplsignal-0.2.0.dist-info/top_level.txt
mplsignal-0.2.0.dist-info/RECORD
