Metadata-Version: 2.1
Name: mplsignal
Version: 0.2.0
Summary: Matplotlib extension for signal processing-related plots
Author-email: Oscar Gustafsson <oscar.gustafsson@gmail.com>
License: BSD 3-Clause License
Project-URL: Homepage, https://github.com/oscargus/mplsignal
Project-URL: Documentation, https://mplsignal.readthedocs.io/
Platform: any
Classifier: Development Status :: 3 - Alpha
Classifier: Framework :: Matplotlib
Classifier: Intended Audience :: Developers
Classifier: Intended Audience :: Science/Research
Classifier: License :: OSI Approved :: BSD License
Classifier: Programming Language :: Python
Classifier: Programming Language :: Python :: 3
Classifier: Programming Language :: Python :: 3.8
Classifier: Programming Language :: Python :: 3.9
Classifier: Programming Language :: Python :: 3.10
Classifier: Programming Language :: Python :: 3.11
Classifier: Topic :: Scientific/Engineering :: Visualization
Requires-Python: >=3.8
License-File: LICENSE
Requires-Dist: matplotlib
Requires-Dist: adjustText
Provides-Extra: doc
Requires-Dist: sphinx ; extra == 'doc'
Requires-Dist: numpydoc ; extra == 'doc'
Requires-Dist: sphinx-rtd-theme ; extra == 'doc'
Requires-Dist: sphinx-copybutton ; extra == 'doc'
Requires-Dist: sphinx-autobuild ; extra == 'doc'
Requires-Dist: sphinx-gallery (>=0.8.2) ; extra == 'doc'
Requires-Dist: autoapi ; extra == 'doc'
Requires-Dist: furo ; extra == 'doc'
Requires-Dist: scipy ; extra == 'doc'
Provides-Extra: test
Requires-Dist: black ; extra == 'test'
Requires-Dist: pytest ; extra == 'test'
Requires-Dist: pytest-mpl ; extra == 'test'
